Metadata-Version: 2.4
Name: memax
Version: 0.1.1
Summary: Deep memory and sequence modeling in JAX
Home-page: https://github.com/smorad/memax
Author: Steven Morad
Author-email: stevenmorad@gmail.com
Classifier: Programming Language :: Python :: 3
Classifier: License :: OSI Approved :: MIT License
Classifier: Operating System :: OS Independent
Requires-Python: >=3.9
Requires-Dist: jax
Requires-Dist: jaxlib
Requires-Dist: jaxtyping
Requires-Dist: optax
Requires-Dist: beartype
Provides-Extra: equinox
Requires-Dist: equinox; extra == "equinox"
Provides-Extra: flax
Requires-Dist: flax; extra == "flax"
Requires-Dist: please-downgrade-to-python-3.13-for-flax; python_version >= "3.14" and extra == "flax"
Provides-Extra: train
Requires-Dist: datasets; extra == "train"
Requires-Dist: tqdm; extra == "train"
Requires-Dist: pillow; extra == "train"
Requires-Dist: wandb; extra == "train"
Provides-Extra: all
Requires-Dist: equinox; extra == "all"
Requires-Dist: flax; extra == "all"
Requires-Dist: please-downgrade-to-python-3.13-for-flax; python_version >= "3.14" and extra == "all"
Requires-Dist: datasets; extra == "all"
Requires-Dist: tqdm; extra == "all"
Requires-Dist: pillow; extra == "all"
Requires-Dist: wandb; extra == "all"
Provides-Extra: test
Requires-Dist: pytest; extra == "test"
Dynamic: author
Dynamic: author-email
Dynamic: classifier
Dynamic: description
Dynamic: description-content-type
Dynamic: home-page
Dynamic: provides-extra
Dynamic: requires-dist
Dynamic: requires-python
Dynamic: summary
